guangluo_project_manager/actions/project.py
guangluo_project_manager/db.py
guangluo_project_manager/main.py
guangluo_project_manager/template/config.toml
guangluo_project_manager/utils.py
guangluo_project_manager-1.0.1.dist-info/entry_points.txt
guangluo_project_manager-1.0.1.dist-info/METADATA
guangluo_project_manager-1.0.1.dist-info/WHEEL
guangluo_project_manager-1.0.1.dist-info/RECORD
