Metadata-Version: 2.1
Name: guangluo-project-manager
Version: 1.0.1
Summary: 
Author: guangluo
Author-email: guangluo@outlook.com
Requires-Python: >=3.12,<4.0
Classifier: Programming Language :: Python :: 3
Classifier: Programming Language :: Python :: 3.12
Requires-Dist: pony (>=0.7.19,<0.8.0)
Requires-Dist: typer (>=0.12.5,<0.13.0)
